{
    "CENSEOID": "J123456",
    "HICN": "C12345",
    "LABRESULTSCASSETTEID": "********",
    "LABRESULTSCREATED": "2021-04-16 15:16:30.350",
    "LABRESULTSMODIFIED": "2021-04-16 15:16:30.350",
    "LABRESULTSDATERELEASED": "2021-03-23 00:00:00.000",
    "LABRESULTSCOMMENT": "TEST",
    "LABRESULTSDATECOLLECTED": "2021-03-17 00:00:00.000",
    "LABRESULTSDATERECEIVED": "2021-03-22 00:00:00.000",
    "LABRESULTVALUE": "4.8",
    "LABTESTNAME": "R_A1C",
    "RESULTSUNITS": "Percent",
    "LABKITNAME": "HbA1c and LDL-Cholesterol",
    "LABKITDEFAULTCPT": "82044",
    "LOINC": "4548-4",
    "NORMALSLOW": "2",
    "NORMALSHIGH": "6.2",
    "ABNORMALINDICATOR": "N",
    "LABTESTID": "12345",
    "LABRESULTID": "12345",
    "LABTESTPRODUCTID": "17",
    "LABRESULTSSUMMARYROWFILTER": "1",
    "CPT_CODE": "3044F",
    "CREATED": "2021-04-16 15:16:30.350",
    "CLIENTID": "190",
    "FIRSTNAME": "ROGER",
    "LASTNAME": "BOB",
    "DOB": "1950-01-01",
    "id": "9acb86f538c1",
    "_rid": "eDA==",
    "_self": "dbs/ej1KQutWs=/docs/ej1FAKQutWsCAAAAAAAADA==/",
    "_etag": "6345a4950000\"",
    "_attachments": "attachments/",
    "_ts": 9999999
}